pycric_predict/__init__.py
pycric_predict/pycric_predict.py
pycric_predict-0.0.1.dist-info/METADATA
pycric_predict-0.0.1.dist-info/WHEEL
pycric_predict-0.0.1.dist-info/top_level.txt
pycric_predict-0.0.1.dist-info/RECORD
