Metadata-Version: 2.1
Name: pycric-predict
Version: 0.0.1
Summary: simple test cricket player score prediction via your cricket knowledge
Home-page: UNKNOWN
Author: YusiferZendric (Aditya Singh)
Author-email: <mail@yusiferzendric.com>
License: UNKNOWN
Keywords: python,cricket,test-cricket,score prediction
Platform: UNKNOWN
Classifier: Development Status :: 1 - Planning
Classifier: Intended Audience :: Developers
Classifier: Programming Language :: Python :: 3
Classifier: Operating System :: Unix
Classifier: Operating System :: MacOS :: MacOS X
Classifier: Operating System :: Microsoft :: Windows
